deel/influenciae/__init__.py
deel/influenciae/benchmark/__init__.py
deel/influenciae/benchmark/base_benchmark.py
deel/influenciae/benchmark/cifar10_benchmark.py
deel/influenciae/benchmark/influence_factory.py
deel/influenciae/benchmark/model_resnet.py
deel/influenciae/boundary_based/__init__.py
deel/influenciae/boundary_based/sample_boundary.py
deel/influenciae/boundary_based/weights_boundary.py
deel/influenciae/common/__init__.py
deel/influenciae/common/base_influence.py
deel/influenciae/common/ihvp_factory.py
deel/influenciae/common/inverse_hessian_vector_product.py
deel/influenciae/common/model_wrappers.py
deel/influenciae/influence/__init__.py
deel/influenciae/influence/arnoldi_influence_calculator.py
deel/influenciae/influence/base_group_influence.py
deel/influenciae/influence/first_order_influence_calculator.py
deel/influenciae/influence/second_order_influence_calculator.py
deel/influenciae/plots/__init__.py
deel/influenciae/plots/benchmark.py
deel/influenciae/plots/image.py
deel/influenciae/rps/__init__.py
deel/influenciae/rps/base_representer_point.py
deel/influenciae/rps/rps_l2.py
deel/influenciae/rps/rps_lje.py
deel/influenciae/trac_in/__init__.py
deel/influenciae/trac_in/tracin.py
deel/influenciae/types/__init__.py
deel/influenciae/utils/__init__.py
deel/influenciae/utils/backtracking_line_search.py
deel/influenciae/utils/conjugate_gradients.py
deel/influenciae/utils/nearest_neighbors.py
deel/influenciae/utils/sorted_dict.py
deel/influenciae/utils/tf_operations.py
Influenciae-0.3.0.dist-info/LICENSE
Influenciae-0.3.0.dist-info/METADATA
Influenciae-0.3.0.dist-info/WHEEL
Influenciae-0.3.0.dist-info/top_level.txt
Influenciae-0.3.0.dist-info/RECORD
